Kryon/__init__.py
Kryon/Database/__init__.py
Kryon/Database/base.py
Kryon/Database/local.py
Kryon/Database/mongo.py
Kryon/Database/vector.py
Kryon/core/agent.py
Kryon/core/memory.py
Kryon/core/predefined_tools.py
Kryon/core/task.py
Kryon/core/tool.py
Kryon/examples/basic_agent.py
Kryon/examples/hello_agent.py
Kryon/examples/multi_backend_demo.py
Kryon/examples/simple_multi_memory.py
Kryon/llms/base.py
Kryon/llms/claude_llm.py
Kryon/llms/gemini_llm.py
Kryon/llms/groq_llm.py
Kryon/llms/openai_llm.py
kryon_ai-1.2.1.dist-info/licenses/LICENSE
kryon_ai-1.2.1.dist-info/METADATA
kryon_ai-1.2.1.dist-info/WHEEL
kryon_ai-1.2.1.dist-info/top_level.txt
kryon_ai-1.2.1.dist-info/RECORD
