Metadata-Version: 2.4
Name: kryon-ai
Version: 1.2.1
Summary: Kryon AI Multi-Backend Agent Framework
Home-page: https://github.com/syedfarith/kryon-ai
Author: Syed Farith C
Author-email: Syed Farith <syedfarith1351@gmail.com>
License: MIT
Classifier: Programming Language :: Python :: 3
Classifier: License :: OSI Approved :: MIT License
Classifier: Operating System :: OS Independent
Requires-Python: >=3.10
License-File: LICENSE
Requires-Dist: requests>=2.32.0
Requires-Dist: numpy>=1.24.0
Requires-Dist: pydantic>=1.10.2
Requires-Dist: python-dotenv>=1.0.0
Requires-Dist: openai>=1.0.0
Requires-Dist: anthropic>=0.6.0
Requires-Dist: google-generativeai>=0.1.0
Requires-Dist: groq>=0.0.2
Requires-Dist: pymongo>=4.4.0
Requires-Dist: tinydb>=4.7.0
Requires-Dist: sqlalchemy>=2.0.0
Requires-Dist: faiss-cpu>=1.7.4
Requires-Dist: python-dotenv>=1.0.0
Provides-Extra: mongo
Requires-Dist: pymongo; extra == "mongo"
Provides-Extra: vector
Requires-Dist: chromadb; extra == "vector"
Requires-Dist: openai; extra == "vector"
Provides-Extra: all
Requires-Dist: pymongo; extra == "all"
Requires-Dist: chromadb; extra == "all"
Requires-Dist: openai; extra == "all"
Dynamic: author
Dynamic: home-page
Dynamic: license-file
Dynamic: requires-python
